README.md
setup.cfg
setup.py
GabTools.egg-info/PKG-INFO
GabTools.egg-info/SOURCES.txt
GabTools.egg-info/dependency_links.txt
GabTools.egg-info/top_level.txt
gabtools/__init__.py
gabtools/maths.py
test/test_maths.py