Metadata-Version: 1.0
Name: GabTools
Version: 0.1.8
Summary: Diverse Python Utilities
Home-page: https://www.github.com/gabrielfortin/gabtools
Author: Gabriel Fortin
Author-email: gabriel.fortin97@gmail.com
License: UNKNOWN
Platform: UNKNOWN
